pyESI/__init__.py
pyESI/ensemble.py
pyESI/mondrian_tree.py
test/__init__.py
test/test_boundingbox.py
test/test_forest.py
test/test_partition.py
pyESI-0.0.1.dist-info/LICENSE
pyESI-0.0.1.dist-info/METADATA
pyESI-0.0.1.dist-info/WHEEL
pyESI-0.0.1.dist-info/top_level.txt
pyESI-0.0.1.dist-info/RECORD
