Metadata-Version: 2.1
Name: pyESI
Version: 0.0.1
Summary: Ensemble Spatial Interpolation module for Python
Home-page: UNKNOWN
Author: ALGES Lab
Author-email: contacto@alges.cl
License: MIT
Keywords: esi,esi-gok,esi-idw,ensemble spatial interpolation
Platform: UNKNOWN
Classifier: License :: OSI Approved :: MIT License
Classifier: Programming Language :: Python :: 3
Classifier: Operating System :: OS Independent
Requires-Python: >=3.6
Requires-Dist: numpy
Requires-Dist: pandas
Requires-Dist: pytest
